{
  "version": "7",
  "dialect": "mysql",
  "entries": [
    {
      "idx": 0,
      "version": "5",
      "when": 1766654758607,
      "tag": "0000_redundant_angel",
      "breakpoints": true
    },
    {
      "idx": 1,
      "version": "5",
      "when": 1766655020715,
      "tag": "0001_brainy_slayback",
      "breakpoints": true
    },
    {
      "idx": 2,
      "version": "5",
      "when": 1766655786357,
      "tag": "0002_petite_brood",
      "breakpoints": true
    },
    {
      "idx": 3,
      "version": "5",
      "when": 1766655879214,
      "tag": "0003_skinny_omega_sentinel",
      "breakpoints": true
    }
  ]
}